{
 "items": [
  {
    "id": "FJGvuHvSQliJF5ph9ev6jQ",
    "url": "https://remote.co/job/high-tech-executive-recruiting-contractor/",
    "title": "High-Tech Executive Recruiting Contractor",
    "tags": [
      "DBG:surround``OR(locat, anywher, base, resid) 7W usa",
      "DBG:surround``work 2W from 2W home 4W OR(staff,cowork,offic,posit)",
      "REMOTE1/100",
      "TECH1/unknown",
      "TITLE1/HR",
      "TZ/America"
    ],
    "tagsNames1": [
      "American time zones"
    ],
    "tagsNames2": [
      "unknown"
    ],
    "hiringOrganization": {
      "name": "UNSET",
      "sameAs": "UNSET"
    },
    "salary": {
      "currency": "UNSET",
      "minValue": 0,
      "maxValue": 0,
      "info": "",
      "unit": "UNSET",
      "isEquity": false
    },
    "employmentType": "UNSET",
    "published": "Jul 30, 2018 4:52:54 PM",
    "validThrough": "Jan 1, 1970 1:00:00 AM",
    "content": "<h2>High-Tech Executive Recruiting Contractor at <span>CyberEdge Group</span></h2><div><span><i></i> Remote</span>         | <span> Freelance </span></div><div>            <ul><li>Washington, DC, USA</li><li>Contract</li></ul><p><strong>LOCATION:</strong></p><p><strong>Your home office anywhere in the United States</strong></p><p><strong>DESCRIPTION:</strong></p><p>CyberEdge Group (http://www.cyber-edge.com) is an award-winning marketing and research consulting firm serving software and hardware vendors in the high-tech industry. Our clients are the “who’s who” of the IT world, including Microsoft, HPE, Dell, VMware, Red Hat, Citrix, Juniper, Palo Alto Networks, and dozens more.</p><p><strong>CyberEdge is currently recruiting experienced high-tech executive recruiting contractors based in the United States&nbsp;</strong>to service our 80+ clients. Responsibilities may include:</p><ul><li>Contingent-based (commission only) searches for high-tech vendor marketing personnel, including:<ul><li>CMO or VP / Director of marketing</li><li>Product marketing managers</li><li>Product managers</li><li>Marketing communications managers</li><li>Corporate communications managers</li><li>Channel marketing managers</li><li>Event marketing managers</li></ul></li><li>Provide a variety of recruiting services on a retainer basis for 20, 30, or 40 hours per week for a minimum of three months</li></ul><p><strong>REQUIREMENTS:</strong></p><ul><li>Minimum of 10 years of high-tech recruiting experience</li><li>B.S. or B.A. undergraduate degree</li><li>An existing network of high-tech marketing personnel</li><li>Ability to fully understand position requirements and candidate prerequisites</li><li>Willingness to screen candidates by phone prior to client submission</li><li>Excellent communication and client-management skills</li><li><strong>Available home office space with computer, software, printer, and Internet access</strong></li></ul><p><strong>BENEFITS:</strong></p><ul><li><strong>Competitive compensation –&nbsp;</strong>CyberEdge consultants are well compensated and don’t need to invest non-billable time locating new projects.</li><li><strong>Frequent projects</strong>&nbsp;– CyberEdge is growing rapidly. Once you’re assigned to an account, repeat projects are consistently assigned to you.</li><li><strong>Reliable payments</strong>&nbsp;– CyberEdge contractors are always paid on time, usually within 7 to 10 days of invoice receipt.</li><li><strong>Work at home – CyberEdge contractors work primarily from their home offices throughout the United States.</strong></li><li><strong>Flexible work hours – Most of our client engagements enable you to set your own schedule.</strong></li></ul>        </div><div>        <a href='https://cyberedge.applicantpro.com/jobs/848576.html' rel='nofollow'>Apply for job</a>    </div>"
  },
  {
    "id": "DbeAl1uCTlqsQwJAJLjCiQ",
    "url": "https://angel.co/consensys/jobs/231931-human-resources-and-recruiting-coordinator",
    "title": "Human Resources and Recruiting Coordinator",
    "tags": [
      "Brooklyn",
      "DBG:surround``OR(pacif, pst, pdt, western, california, losangel, sanfrancisco, paloalto, sanmateo) 3W OR(time,timezon)",
      "DBG:surround``remot 3N ( OR(employe,develop,engin,team,role,employment,workmat) OR compani OR worldwide)",
      "Full Time",
      "H.R.",
      "REMOTE1/100",
      "Remote OK",
      "TECH1/unknown",
      "TITLE1/HR",
      "TZ/America/West"
    ],
    "tagsNames1": [
      "US Pacific time zone"
    ],
    "tagsNames2": [
      "unknown"
    ],
    "hiringOrganization": {
      "name": "UNSET",
      "sameAs": "UNSET"
    },
    "salary": {
      "currency": "USD",
      "minValue": 50000,
      "maxValue": 55000,
      "info": "0.01% – 0.01%",
      "unit": "YEAR",
      "isEquity": false
    },
    "employmentType": "UNSET",
    "published": "Jul 30, 2018 9:42:58 AM",
    "validThrough": "Jan 1, 1970 1:00:00 AM",
    "content": "Human Resources and Recruiting Coordinator Job at ConsenSys - AngelList<div><div><div><div><div><div><a title=&quot;ConsenSys&quot; href='https://angel.co/consensys/jobs' rel='nofollow'></a></div><div></div><ul><li><span>ConsenSys</span></li><li><span>Product</span></li><li><span>Jobs</span></li><li><span>Team</span></li></ul><div><div><div><div><div><a rel='nofollow'><span></span>Applied</a></div></div><div></div><div><span>Apply Now</span><div><div></div><div></div><div><div><div><div>Add a message to ConsenSys</div>Apply<div></div></div></div></div></div></div><div></div></div></div><div><div><span>Share</span></div></div></div></div></div></div></div><div><div><div></div></div><div><div><div><a title=&quot;ConsenSys&quot; href='https://angel.co/consensys' rel='nofollow'></a></div><div><h2>Human Resources and Recruiting Coordinator at ConsenSys</h2><div>Brooklyn, Remote · Full Time</div><div><div><div><div><div><div><span>We're a fluid organization comprised of deep thinkers from a variety of backgrounds.<span>Read More</span></span></div><div><p>We're a fluid organization comprised of deep thinkers from a variety of backgrounds.</p><p>We're passionate about our work and are looking to find others who are interested in building solutions for an emerging, digitally-integrated economy.&nbsp;</p><p>Please see our website for current opportunities. <a href='https://consensys.net/open-positions/' rel='nofollow'>https://consensys.net/open-positions/</a></p></div></div></div></div></div></div><div><div><div><div><div><a rel='nofollow'><span></span>Applied</a></div></div><div></div><div><span>Apply to ConsenSys</span><div><div></div><div></div><div><div><div><div>Add a message to ConsenSys</div>Apply<div></div></div></div></div></div></div><div></div></div></div></div></div></div><div></div></div></div><div><div><div><h3>Job Description</h3></div><div><div><p>Apply Here: </p><p>ConsenSys is a venture production studio focused on building and scaling tools and enterprise software products powered by Ethereum. Our mission is to use these solutions to power the emerging economic, social, and political operating systems of the planet.</p><p>Our teams are busy at work building the future of identity, financial markets, commerce, the music industry, security and infrastructure, and more. To accomplish this, we’ve built out a flat organizational structure which we call the ConsenSys Mesh; a network of individuals &amp; teams working autonomously and towards the same goal. The MeshOps team is responsible for designing and implementing “Meshocracy”, our own operational &amp; company structure loosely based on the principles of holacracy. If you are someone that thrives in a fast-paced environment where being self-directed, determined, and resilient are a requirement, we would love for you to join us.</p><p>The Role</p><p>The Human Resources and Recruiting Coordinator is an integral member of our team!  We need help telling our story around the world!  In this role you will develop a solid foundation of knowledge and experience as part of a greater global team serving countless internal customers and projects on 6 continents. You will have the opportunity to build candidate relationships, and partner with recruiters, human resources and hiring managers. The ideal candidate seeks career growth within Recruiting and/or Human Resources and will provide support in many different areas.  This is truly a choose your own destiny situation, and a chance for ownership.  This role will grow and evolve as ConsenSys grows and incolves</p><p>Build excellent relationships across our organization<br>Create welcome packages and kits for new hires<br>Coordinate interview activities on-campus and in-house including, but not limited to, scheduling and calendar invites; interview confirmation emails; reserving interview rooms and telephone/video conference (when necessary); and candidate debrief calls/meetings<br>Schedule and coordinate logistics for all campus recruiting events, e.g. RSVPs, payment/check requests, calendar invites, etc.<br>Manage inventory for all recruiting swag and ensure all swag is readily available.<br>Coordinate offer letter process and as well as onboarding set-up<br>Provide support on special projects and initiatives<br>Assist with the internship program and internal events<br>Assist with wellness endeavors<br>Required Skills:</p><p>Meticulous attention to detail and strong organizational skills with proven ability to prioritize and complete projects within deadlines<br>Self-starter who loves taking initiative<br>Creative problem solver<br>Discreet and able to manage sensitive information<br>Flexibility, high energy and a positive attitude<br>Prior experience in a Recruiting or Human Resources department is preferred<br>Familiarity with applicant tracking systems, HR systems and social media is preferred<br>Ability to focus on the details, but also understand the bigger picture<br>Bonus Points:</p><p>Interest in new technology, Blockchain, and/or Ethereum<br>Humble, kind, and doesn't take themselves too seriously</p></div></div><div><div>Compensation</div><div>$50K–$55K<br>0.01%–0.01%</div><div>Visa Sponsorship</div><div>Available</div></div><div><div><div><div><div><a rel='nofollow'><span></span>Applied</a></div></div><div></div><div><span>Apply Now</span><div><div></div><div></div><div><div><div><div>Add a message to ConsenSys</div>Apply<div></div></div></div></div></div></div><div></div></div></div></div></div></div><div><div><div><div><h4>People also viewed</h4></div><div><div><div><a href='https://angel.co/forkable/jobs/110183-awesome-people?src=rec' rel='nofollow'></a></div><div><a href='https://angel.co/forkable/jobs/110183-awesome-people?src=rec' rel='nofollow'>Awesome People</a></div><div><a href='https://angel.co/forkable/jobs/110183-awesome-people?src=rec' rel='nofollow'>Forkable</a></div><div>San Francisco</div></div></div><div><div><div><a href='https://angel.co/health-recovery-solutions-1/jobs/347991-people-operations-associate?src=rec' rel='nofollow'></a></div><div><a href='https://angel.co/health-recovery-solutions-1/jobs/347991-people-operations-associate?src=rec' rel='nofollow'>People Operations Associate</a></div><div><a href='https://angel.co/health-recovery-solutions-1/jobs/347991-people-operations-associate?src=rec' rel='nofollow'>Health Recovery Solutions</a></div><div>Hoboken, New York City</div></div></div><div><div><div><a href='https://angel.co/bamboo-talent/jobs/82075-recruiting-coordinator?src=rec' rel='nofollow'></a></div><div><a href='https://angel.co/bamboo-talent/jobs/82075-recruiting-coordinator?src=rec' rel='nofollow'>Recruiting Coordinator</a></div><div><a href='https://angel.co/bamboo-talent/jobs/82075-recruiting-coordinator?src=rec' rel='nofollow'>Bamboo Talent</a></div><div>New York City</div></div></div><div><div><div><a href='https://angel.co/dultcoin-system/jobs/305555-human-resources-recruiting-manager?src=rec' rel='nofollow'></a></div><div><a href='https://angel.co/dultcoin-system/jobs/305555-human-resources-recruiting-manager?src=rec' rel='nofollow'>Human Resources/Recruiting Manager</a></div><div><a href='https://angel.co/dultcoin-system/jobs/305555-human-resources-recruiting-manager?src=rec' rel='nofollow'>Dultcoin System</a></div><div>Florida, New York City, California</div></div></div><div><div><div><a href='https://angel.co/joinopus/jobs/329095-talent-partner?src=rec' rel='nofollow'></a></div><div><a href='https://angel.co/joinopus/jobs/329095-talent-partner?src=rec' rel='nofollow'>Talent Partner</a></div><div><a href='https://angel.co/joinopus/jobs/329095-talent-partner?src=rec' rel='nofollow'>Opus</a></div><div>Remote, Chicago</div></div></div><div><div><div><a href='https://angel.co/palantir-technologies/jobs/323415-people-partner?src=rec' rel='nofollow'></a></div><div><a href='https://angel.co/palantir-technologies/jobs/323415-people-partner?src=rec' rel='nofollow'>People Partner</a></div><div><a href='https://angel.co/palantir-technologies/jobs/323415-people-partner?src=rec' rel='nofollow'>Palantir Technologies</a></div><div>Palo Alto, London</div></div></div><div><div><div><a href='https://angel.co/retain-hr/jobs/213751-recruiter?src=rec' rel='nofollow'></a></div><div><a href='https://angel.co/retain-hr/jobs/213751-recruiter?src=rec' rel='nofollow'>Recruiter</a></div><div><a href='https://angel.co/retain-hr/jobs/213751-recruiter?src=rec' rel='nofollow'>RetainHR</a></div><div>San Francisco, Mountain View</div></div></div><div><div><div><a href='https://angel.co/mlg-blockchain/jobs/329541-hr-director?src=rec' rel='nofollow'></a></div><div><a href='https://angel.co/mlg-blockchain/jobs/329541-hr-director?src=rec' rel='nofollow'>HR Director</a></div><div><a href='https://angel.co/mlg-blockchain/jobs/329541-hr-director?src=rec' rel='nofollow'>MLG Blockchain</a></div><div>Toronto, Montreal, New York City</div></div></div><div><div><div><a href='https://angel.co/process-street/jobs/332963-hr-and-recruitment-assistant-remote-candidate-sourcing-and-screening?src=rec' rel='nofollow'></a></div><div><a href='https://angel.co/process-street/jobs/332963-hr-and-recruitment-assistant-remote-candidate-sourcing-and-screening?src=rec' rel='nofollow'>HR and Recruitment Assistant - R...</a></div><div><a href='https://angel.co/process-street/jobs/332963-hr-and-recruitment-assistant-remote-candidate-sourcing-and-screening?src=rec' rel='nofollow'>Process Street</a></div><div>Argentina, Brazil, Chile</div></div></div></div></div></div><div><div><div><div><h3>What We're Building</h3></div><div><div><p>ConsenSys is a blockchain venture production studio building decentralized applications, mostly on Ethereum. We are currently building foundational tools for emerging business models in the cryptocurrency or Bitcoin 2.0 space. These tools will be packaged into separate ventures that are individually funded and skinned for different business niches.</p><p>ConsenSys is presently comprised of a number of core personnel — some of whom are based in New York City, but several are in other cities around the world — who are focussed on the identification, acquisition, and development of talent and projects, in addition to the development of our own internal projects and some focus on consulting work.</p><p>ConsenSys spawns, coordinates, incubates and accelerates single purpose vehicles (SPVs) through internal development, acquisitions, investments, or the formation of joint ventures.</p></div></div><div><div><div><div><div></div><div>Hiring in <span>Brooklyn</span>, Remote OK</div><div></div></div><div><div></div><div>501-1000 Employees</div><div></div></div><div><div></div><span>Blockchains</span></div><div><div></div><a href='http://twitter.com/@ConsenSys' rel='nofollow'>@ConsenSys</a></div><div><div></div><a href='https://medium.com/@ConsenSys' rel='nofollow'>https://medium.com/@ConsenSys</a></div><div><div></div><a href='http://ConsenSys.net' rel='nofollow'>ConsenSys.net</a></div></div></div></div></div></div></div><div><div><div><h3>Other Jobs at ConsenSys</h3><ul><li><div>Software Engineering Jobs</div><div><div><div><div><a href='https://angel.co/consensys/jobs/203793-security-engineer-lead-smart-contracts' rel='nofollow'>Security Engineer / Lead - Smart Contracts</a><div>Brooklyn·Full Time<span></span><span>·$90K – $120K · 0.01% – 0.01%</span></div></div><div><div><div><div><div><a rel='nofollow'><span></span>Applied</a></div></div><div></div><div><span>Apply</span><div><div></div><div></div><div><div><div><div>Add a message to ConsenSys</div>Apply<div></div></div></div></div></div></div><div></div></div></div></div></div></div><div><div><div><a href='https://angel.co/consensys/jobs/344978-support-engineer' rel='nofollow'>Support Engineer</a><div>Boston·Full Time<span></span><span>·$70K – $90K · 0.0% – 0.01%</span></div></div><div><div><div><div><div><a rel='nofollow'><span></span>Applied</a></div></div><div></div><div><span>Apply</span><div><div></div><div></div><div><div><div><div>Add a message to ConsenSys</div>Apply<div></div></div></div></div></div></div><div></div></div></div></div></div></div><div><div><div><a href='https://angel.co/consensys/jobs/345709-lead-quality-assurance-balanc3' rel='nofollow'>Lead Quality Assurance (Balanc3)</a><div>Brooklyn·Full Time<span></span><span>·$100K – $150K · No Equity</span></div></div><div><div><div><div><div><a rel='nofollow'><span></span>Applied</a></div></div><div></div><div><span>Apply</span><div><div></div><div></div><div><div><div><div>Add a message to ConsenSys</div>Apply<div></div></div></div></div></div></div><div></div></div></div></div></div></div><div><div><div><a href='https://angel.co/consensys/jobs/345711-lead-backend-engineer-balanc3' rel='nofollow'>Lead Backend Engineer (Balanc3)</a><div>Brooklyn·Full Time<span></span><span>·$110K – $170K · No Equity</span></div></div><div><div><div><div><div><a rel='nofollow'><span></span>Applied</a></div></div><div></div><div><span>Apply</span><div><div></div><div></div><div><div><div><div>Add a message to ConsenSys</div>Apply<div></div></div></div></div></div></div><div></div></div></div></div></div></div><div><div><div><a href='https://angel.co/consensys/jobs/351437-backend-engineer' rel='nofollow'>Backend Engineer</a><div>Brooklyn·Full Time<span></span><span>·$100K – $180K · 0.001% – 1.0%</span></div></div><div><div><div><div><div><a rel='nofollow'><span></span>Applied</a></div></div><div></div><div><span>Apply</span><div><div></div><div></div><div><div><div><div>Add a message to ConsenSys</div>Apply<div></div></div></div></div></div></div><div></div></div></div></div></div></div><div><div><div><a href='https://angel.co/consensys/jobs/369513-front-end-developer-marketing' rel='nofollow'>Front End Developer (Marketing)</a><div>Brooklyn, San Francisco·Full Time<span></span><span>·$90K – $120K · No Equity</span></div></div><div><div><div><div><div><a rel='nofollow'><span></span>Applied</a></div></div><div></div><div><span>Apply</span><div><div></div><div></div><div><div><div><div>Add a message to ConsenSys</div>Apply<div></div></div></div></div></div></div><div></div></div></div></div></div></div><div><div><div><a href='https://angel.co/consensys/jobs/376027-front-end-developer' rel='nofollow'>Front End Developer</a><div>Remote, Brooklyn·Full Time<span></span><span>·$90K – $120K · 0.01% – 0.01%</span></div></div><div><div><div><div><div><a rel='nofollow'><span></span>Applied</a></div></div><div></div><div><span>Apply</span><div><div></div><div></div><div><div><div><div>Add a message to ConsenSys</div>Apply<div></div></div></div></div></div></div><div></div></div></div></div></div></div><div><div><div><a href='https://angel.co/consensys/jobs/376029-senior-full-stack-developer' rel='nofollow'>Senior Full Stack Developer</a><div>Remote, Brooklyn·Full Time<span></span><span>·$100K – $130K · 0.01% – 0.01%</span></div></div><div><div><div><div><div><a rel='nofollow'><span></span>Applied</a></div></div><div></div><div><span>Apply</span><div><div></div><div></div><div><div><div><div>Add a message to ConsenSys</div>Apply<div></div></div></div></div></div></div><div></div></div></div></div></div></div><div><div><div><a href='https://angel.co/consensys/jobs/385210-software-quality-assurance-qa-lead' rel='nofollow'>Software Quality Assurance (QA) Lead</a><div>Singapore, Singapore·Full Time<span></span><span>·$90K – $120K · No Equity</span></div></div><div><div><div><div><div><a rel='nofollow'><span></span>Applied</a></div></div><div></div><div><span>Apply</span><div><div></div><div></div><div><div><div><div>Add a message to ConsenSys</div>Apply<div></div></div></div></div></div></div><div></div></div></div></div></div></div><div><div><div><a href='https://angel.co/consensys/jobs/388019-blockchain-protocol-engineer' rel='nofollow'>Blockchain Protocol Engineer</a><div>Brooklyn·Full Time<span></span><span>·$100K – $180K · No Equity</span></div></div><div><div><div><div><div><a rel='nofollow'><span></span>Applied</a></div></div><div></div><div><span>Apply</span><div><div></div><div></div><div><div><div><div>Add a message to ConsenSys</div>Apply<div></div></div></div></div></div></div><div></div></div></div></div></div></div></div><div></div></li><li><div>Engineering Jobs</div><div><div><div><div><a href='https://angel.co/consensys/jobs/348033-lead-network-operations-engineer' rel='nofollow'>Lead Network Operations Engineer</a><div>Remote, Boston·Full Time<span></span><span>·$90K – $115K · 0.001% – 0.001%</span></div></div><div><div><div><div><div><a rel='nofollow'><span></span>Applied</a></div></div><div></div><div><span>Apply</span><div><div></div><div></div><div><div><div><div>Add a message to ConsenSys</div>Apply<div></div></div></div></div></div></div><div></div></div></div></div></div></div></div><div></div></li><li><div>Marketing Jobs</div><div><div><div><div><a href='https://angel.co/consensys/jobs/332062-events-manager' rel='nofollow'>Events Manager</a><div>Toronto·Full Time<span></span><span>·$75K – $83K · 0.01% – 0.01%</span></div></div><div><div><div><div><div><a rel='nofollow'><span></span>Applied</a></div></div><div></div><div><span>Apply</span><div><div></div><div></div><div><div><div><div>Add a message to ConsenSys</div>Apply<div></div></div></div></div></div></div><div></div></div></div></div></div></div></div><div></div></li><li><div>Operations Jobs</div><div><div><div><div><a href='https://angel.co/consensys/jobs/345614-network-operations-engineer-customer-success' rel='nofollow'>Network Operations Engineer (Customer Success)</a><div>Boston·Full Time<span></span><span>·$40K – $50K · 0.01% – 0.01%</span></div></div><div><div><div><div><div><a rel='nofollow'><span></span>Applied</a></div></div><div></div><div><span>Apply</span><div><div></div><div></div><div><div><div><div>Add a message to ConsenSys</div>Apply<div></div></div></div></div></div></div><div></div></div></div></div></div></div><div><div><div><a href='https://angel.co/consensys/jobs/366882-learning-development-lead' rel='nofollow'>Learning &amp; Development Lead</a><div>Brooklyn·Full Time<span></span><span>·$180K – $190K · 0.001% – 0.001%</span></div></div><div><div><div><div><div><a rel='nofollow'><span></span>Applied</a></div></div><div></div><div><span>Apply</span><div><div></div><div></div><div><div><div><div>Add a message to ConsenSys</div>Apply<div></div></div></div></div></div></div><div></div></div></div></div></div></div><div><div><div><a href='https://angel.co/consensys/jobs/367843-self-managing-systems-designer-facilitator' rel='nofollow'>Self-Managing Systems Designer &amp; Facilitator</a><div>Brooklyn·Full Time<span></span><span>·$135K – $145K · 0.001% – 0.001%</span></div></div><div><div><div><div><div><a rel='nofollow'><span></span>Applied</a></div></div><div></div><div><span>Apply</span><div><div></div><div></div><div><div><div><div>Add a message to ConsenSys</div>Apply<div></div></div></div></div></div></div><div></div></div></div></div></div></div><div><div><div><a href='https://angel.co/consensys/jobs/367859-self-management-curriculum-designer-content-creator' rel='nofollow'>Self-Management Curriculum Designer/Content Creator</a><div>Brooklyn, Remote·Full Time<span></span><span>·$50K – $60K · 0.001% – 0.001%</span></div></div><div><div><div><div><div><a rel='nofollow'><span></span>Applied</a></div></div><div></div><div><span>Apply</span><div><div></div><div></div><div><div><div><div>Add a message to ConsenSys</div>Apply<div></div></div></div></div></div></div><div></div></div></div></div></div></div><div><div><div><a href='https://angel.co/consensys/jobs/367904-talent-operations' rel='nofollow'>Talent Operations</a><div>Brooklyn, San Francisco, Toronto·Full Time<span></span><span>·$50K – $60K · 0.001% – 0.001%</span></div></div><div><div><div><div><div><a rel='nofollow'><span></span>Applied</a></div></div><div></div><div><span>Apply</span><div><div></div><div></div><div><div><div><div>Add a message to ConsenSys</div>Apply<div></div></div></div></div></div></div><div></div></div></div></div></div></div><div><div><div><a href='https://angel.co/consensys/jobs/376369-customer-success-manager' rel='nofollow'>Customer Success Manager</a><div>Boston, Romania, Remote·Full Time<span></span><span>·$70K – $80K · 0.01% – 0.01%</span></div></div><div><div><div><div><div><a rel='nofollow'><span></span>Applied</a></div></div><div></div><div><span>Apply</span><div><div></div><div></div><div><div><div><div>Add a message to ConsenSys</div>Apply<div></div></div></div></div></div></div><div></div></div></div></div></div></div></div><div></div></li><li><div>Other Jobs</div><div><div><div><div><a href='https://angel.co/consensys/jobs/329943-acquisitions-and-asset-management-analyst-pangea' rel='nofollow'>Acquisitions and Asset Management Analyst (Pangea)</a><div>Brooklyn·Full Time<span></span><span>·$75K – $90K · 0.01% – 0.01%</span></div></div><div><div><div><div><div><a rel='nofollow'><span></span>Applied</a></div></div><div></div><div><span>Apply</span><div><div></div><div></div><div><div><div><div>Add a message to ConsenSys</div>Apply<div></div></div></div></div></div></div><div></div></div></div></div></div></div><div><div><div><a href='https://angel.co/consensys/jobs/366867-business-operations-associate-global-operations' rel='nofollow'>Business Operations Associate, Global Operations</a><div>Brooklyn·Full Time<span></span><span>·$70K – $80K · 0.001% – 0.001%</span></div></div><div><div><div><div><div><a rel='nofollow'><span></span>Applied</a></div></div><div></div><div><span>Apply</span><div><div></div><div></div><div><div><div><div>Add a message to ConsenSys</div>Apply<div></div></div></div></div></div></div><div></div></div></div></div></div></div><div><div><div><a href='https://angel.co/consensys/jobs/385211-business-analyst-strategy-consultant' rel='nofollow'>Business Analyst/Strategy Consultant</a><div>Singapore, Singapore·Full Time<span></span><span>·$90K – $110K · No Equity</span></div></div><div><div><div><div><div><a rel='nofollow'><span></span>Applied</a></div></div><div></div><div><span>Apply</span><div><div></div><div></div><div><div><div><div>Add a message to ConsenSys</div>Apply<div></div></div></div></div></div></div><div></div></div></div></div></div></div></div><div></div></li></ul></div></div></div><div><div><div><h3>ConsenSys Team</h3><div><div><div><div><div><a href='https://angel.co/joseph-lubin-1' rel='nofollow'></a></div><div><div><a href='https://angel.co/joseph-lubin-1' rel='nofollow'>Joseph Lubin</a></div></div></div><div><div><a href='https://angel.co/ash-hogan' rel='nofollow'></a></div><div><div><a href='https://angel.co/ash-hogan' rel='nofollow'>Ash Hogan</a><span>,</span></div><div>Global Talent Acquisition Leader, Solutions at ConsenSys | Founder at emplyd | Advisor</div></div></div><div><div><a href='https://angel.co/ash-egan' rel='nofollow'></a></div><div><div><a href='https://angel.co/ash-egan' rel='nofollow'>Ash Egan</a><span>,</span></div><div>VC <a href='https://angel.co/consensys' title=&quot;ConsenSys&quot; rel='nofollow'><span>@</span><span>ConsenSys</span></a> </div></div></div><div><div><a href='https://angel.co/kendall-cole-1' rel='nofollow'></a></div><div><div><a href='https://angel.co/kendall-cole-1' rel='nofollow'>Kendall Cole</a><span>,</span></div><div>Building kauri.io <a href='https://angel.co/consensys' title=&quot;ConsenSys&quot; rel='nofollow'><span>@</span><span>ConsenSys</span></a> . <a href='https://angel.co/entrepreneur-first' title=&quot;Entrepreneur First&quot; rel='nofollow'><span>@</span><span>Entrepreneur First</span></a> EF 7. Co-Founder <a href='https://angel.co/oilfront' title=&quot;OilFront&quot; rel='nofollow'><span>@</span><span>OilFront</span></a> <a href='https://angel.co/jobfire' title=&quot;EntryWire&quot; rel='nofollow'><span>@</span><span>EntryWire</span></a> . <a href='https://angel.co/startupchile' title=&quot;Start-Up Chile&quot; rel='nofollow'><span>@</span><span>Start-Up Chile</span></a>  Gen 13. Former engineer <a href='https://angel.co/unbabel' title=&quot;Unbabel&quot; rel='nofollow'><span>@</span><span>Unbabel</span></a>  and <a href='https://angel.co/veenome' title=&quot;Veenome&quot; rel='nofollow'><span>@</span><span>Veenome</span></a>. UVA 2013</div></div></div><div><div><a href='https://angel.co/eric-morrow' rel='nofollow'></a></div><div><div><a href='https://angel.co/eric-morrow' rel='nofollow'>Eric Morrow</a><span>,</span></div><div>Digital Marketing specialist, focused on helping startups attract customers.</div></div></div><div><div><a href='https://angel.co/juanllanos' rel='nofollow'></a></div><div><div><a href='https://angel.co/juanllanos' rel='nofollow'>Juan Llanos</a><span>,</span></div><div>Founder <a href='https://angel.co/unidos-financial-services' title=&quot;Unidos Financial Services&quot; rel='nofollow'><span>@</span><span>Unidos Financial Services</span></a> • Studied at <a href='https://angel.co/universidad-de-palermo' rel='nofollow'><span>@</span><span>Universidad de Palermo</span></a>, <a href='https://angel.co/virginia-commonwealth-university' rel='nofollow'><span>@</span><span>Virginia Commonwealth University</span></a></div></div></div></div></div></div><div></div><div><span>See More</span><span></span></div><div></div></div></div></div><div><div><div><div><div>ConsenSys is one of 26,093 startups hiring on AngelList</div><div></div></div><div><div><span>Browse All Startup Jobs</span><a href='https://angel.co/recruiting/signup?src=job-showcase' rel='nofollow'>Post a Job</a></div></div><div><span>Help</span>·<span>Terms</span>·<span>Jobs by location</span><span>Problem?<span>Report this company</span></span></div></div></div></div></div><div></div>"
  },
  {
    "id": "1E1TqV0rQwSJkJAkI6TXxw",
    "url": "https://angel.co/consensys/jobs/367904-talent-operations",
    "title": "Talent Operations",
    "tags": [
      "Brooklyn",
      "DBG:surround``remot 3N ( OR(employe,develop,engin,team,role,employment,workmat) OR compani OR worldwide)",
      "Full Time",
      "H.R.",
      "REMOTE1/100",
      "Recruiter",
      "Remote OK",
      "San Francisco",
      "TECH1/unknown",
      "TITLE1/HR",
      "TZ/unknown",
      "Toronto"
    ],
    "tagsNames1": [],
    "tagsNames2": [
      "unknown"
    ],
    "hiringOrganization": {
      "name": "UNSET",
      "sameAs": "UNSET"
    },
    "salary": {
      "currency": "USD",
      "minValue": 50000,
      "maxValue": 60000,
      "info": "0.001% – 0.001%",
      "unit": "YEAR",
      "isEquity": false
    },
    "employmentType": "UNSET",
    "published": "Jul 30, 2018 9:42:58 AM",
    "validThrough": "Jan 1, 1970 1:00:00 AM",
    "content": "Talent Operations Job at ConsenSys - AngelList<div><div><div><div><div><div><a title=&quot;ConsenSys&quot; href='https://angel.co/consensys/jobs' rel='nofollow'></a></div><div></div><ul><li><span>ConsenSys</span></li><li><span>Product</span></li><li><span>Jobs</span></li><li><span>Team</span></li></ul><div><div><div><div><div><a rel='nofollow'><span></span>Applied</a></div></div><div></div><div><span>Apply Now</span><div><div></div><div></div><div><div><div><div>Add a message to ConsenSys</div>Apply<div></div></div></div></div></div></div><div></div></div></div><div><div><span>Share</span></div></div></div></div></div></div></div><div><div><div></div></div><div><div><div><a title=&quot;ConsenSys&quot; href='https://angel.co/consensys' rel='nofollow'></a></div><div><h2>Talent Operations at ConsenSys</h2><div>Brooklyn, San Francisco, Toronto, Remote · Full Time</div><div><div><div><div><div><div><span>We're a fluid organization comprised of deep thinkers from a variety of backgrounds.<span>Read More</span></span></div><div><p>We're a fluid organization comprised of deep thinkers from a variety of backgrounds.</p><p>We're passionate about our work and are looking to find others who are interested in building solutions for an emerging, digitally-integrated economy.&nbsp;</p><p>Please see our website for current opportunities. <a href='https://consensys.net/open-positions/' rel='nofollow'>https://consensys.net/open-positions/</a></p></div></div></div></div></div></div><div><div><div><div><div><a rel='nofollow'><span></span>Applied</a></div></div><div></div><div><span>Apply to ConsenSys</span><div><div></div><div></div><div><div><div><div>Add a message to ConsenSys</div>Apply<div></div></div></div></div></div></div><div></div></div></div></div></div></div><div></div></div></div><div><div><div><h3>Job Description</h3></div><div><div><p>ConsenSys is a venture production studio and the leading technology firm in blockchain globally. We deliver products, solutions and platforms built using blockchain technology to transform how business is done in complex network of buyers, suppliers and consumers.</p><p>Our teams are busy at work building the future of identity, financial markets, commerce, the music industry, security, and infrastructure, and more. To accomplish this we've built out a flat organizational structure which we call the ConsenSys Mesh: a network of individuals &amp; teams working autonomously and towards the same goal.  Our mission is to use these decentralized solutions to fundamentally reshape the economic, social, and political operating systems of the planet. If you are someone that thrives in a fast-paced environment where being self-directed, determined, and resilient are a requirement, we would love for you to join us.</p><p>About the role:</p><p>ConsenSys is seeking a Talent Ops who will serve as a primary point of contact for candidates interviewing at ConsenSys and will ensure the full candidate experience runs smoothly. In this exciting role, you will be primarily supporting the Talent team as well as supporting some People functions.</p><p>Responsibilities:</p><p>Correspond with candidates throughout the interview process, including scheduling phone screens, arranging and booking candidate travel, and organizing in-house interviews<br>Prepare the ConsenSys team before all interviews and promptly gather and share feedback with hiring managers<br>Create and update JDs for companies we are growing internally and various service teams within the organization<br>Screen candidate applications from a variety of recruiting platforms<br>Correspond with candidates and provide email updates</p><p>Requirements:</p><p>You have successful experience as a recruiter or as a recruiting coordinator in a quickly changing and/ or high volume environment<br>You're a self-starter and comfortable with ambiguity<br>You're self-directed and strive for a great candidate experience<br>You're exceptionally organized, never letting anything fall through the cracks<br>You have an interest in new technology, Blockchain, and/or Ethereum</p><p>Nice to have:</p><p>+Experience using Greenhouse<br>+Comfortable working with distributed teams</p><p> Here are some of the perks of being part of a unique organization like ConsenSys:</p><p>-The forefront of a revolution. At ConsenSys we fundamentally believe that a next generation of technologies presents the opportunity to create a more just and equitable society.<br>-A dynamic startup environment. ConsenSys is a thought leader in the blockchain space and we are absorbing a significant portion of the mindshare. This is both exciting and challenging, as we learn to scale our organization while adhering to the principles of decentralization.<br>-Continuous learning. You’ll be constantly exposed to new languages, frameworks and ideas from your peers and as you work on different projects -- challenging you to stay at the top of your game.<br>-Deep technical challenges. This entire ecosystem is about 10 years old. Ethereum itself is still a toddler. There is much work to be done before these platforms can scale to the order of millions or billions of users. ConsenSys is building the technology platforms that can get us to those next thresholds of scale.</p></div></div><div><div>Compensation</div><div>$50K–$60K<br>0.001%–0.001%</div><div>Visa Sponsorship</div><div>Not available</div></div><div><div><div><div><div><a rel='nofollow'><span></span>Applied</a></div></div><div></div><div><span>Apply Now</span><div><div></div><div></div><div><div><div><div>Add a message to ConsenSys</div>Apply<div></div></div></div></div></div></div><div></div></div></div></div></div></div><div><div><div><div><h4>People also viewed</h4></div><div><div><div><a href='https://angel.co/proxyclick-1/jobs/344570-senior-account-executive-with-saas-experience-remote?src=rec' rel='nofollow'></a></div><div><a href='https://angel.co/proxyclick-1/jobs/344570-senior-account-executive-with-saas-experience-remote?src=rec' rel='nofollow'>Senior Account Executive with Sa...</a></div><div><a href='https://angel.co/proxyclick-1/jobs/344570-senior-account-executive-with-saas-experience-remote?src=rec' rel='nofollow'>Proxyclick</a></div><div>United States, Canada</div></div></div><div><div><div><a href='https://angel.co/consensys/jobs/231931-human-resources-and-recruiting-coordinator?src=rec' rel='nofollow'></a></div><div><a href='https://angel.co/consensys/jobs/231931-human-resources-and-recruiting-coordinator?src=rec' rel='nofollow'>Human Resources and Recruiting C...</a></div><div><a href='https://angel.co/consensys/jobs/231931-human-resources-and-recruiting-coordinator?src=rec' rel='nofollow'>ConsenSys</a></div><div>Brooklyn</div></div></div><div><div><div><a href='https://angel.co/platterz/jobs/355042-talent-specialist?src=rec' rel='nofollow'></a></div><div><a href='https://angel.co/platterz/jobs/355042-talent-specialist?src=rec' rel='nofollow'>Talent Specialist</a></div><div><a href='https://angel.co/platterz/jobs/355042-talent-specialist?src=rec' rel='nofollow'>Platterz</a></div><div>Toronto, Los Angeles</div></div></div><div><div><div><a href='https://angel.co/process-street/jobs/245231-junior-remote-customer-success-manager?src=rec' rel='nofollow'></a></div><div><a href='https://angel.co/process-street/jobs/245231-junior-remote-customer-success-manager?src=rec' rel='nofollow'>Junior Remote Customer Success M...</a></div><div><a href='https://angel.co/process-street/jobs/245231-junior-remote-customer-success-manager?src=rec' rel='nofollow'>Process Street</a></div><div>Vancouver, Toronto, Austin</div></div></div><div><div><div><a href='https://angel.co/hito-labs/jobs/364625-recruiter-part-time?src=rec' rel='nofollow'></a></div><div><a href='https://angel.co/hito-labs/jobs/364625-recruiter-part-time?src=rec' rel='nofollow'>Recruiter (part-time)</a></div><div><a href='https://angel.co/hito-labs/jobs/364625-recruiter-part-time?src=rec' rel='nofollow'>Hito Labs</a></div><div>New York City, Seattle</div></div></div><div><div><div><a href='https://angel.co/improbable/jobs/80452-technical-recruiters-all-levels-real-world-simulation?src=rec' rel='nofollow'></a></div><div><a href='https://angel.co/improbable/jobs/80452-technical-recruiters-all-levels-real-world-simulation?src=rec' rel='nofollow'>Technical Recruiters - All Level...</a></div><div><a href='https://angel.co/improbable/jobs/80452-technical-recruiters-all-levels-real-world-simulation?src=rec' rel='nofollow'>Improbable</a></div><div>London</div></div></div><div><div><div><a href='https://angel.co/joinopus/jobs/329095-talent-partner?src=rec' rel='nofollow'></a></div><div><a href='https://angel.co/joinopus/jobs/329095-talent-partner?src=rec' rel='nofollow'>Talent Partner</a></div><div><a href='https://angel.co/joinopus/jobs/329095-talent-partner?src=rec' rel='nofollow'>Opus</a></div><div>Remote, Chicago</div></div></div><div><div><div><a href='https://angel.co/opencare/jobs/355795-practice-support-manager?src=rec' rel='nofollow'></a></div><div><a href='https://angel.co/opencare/jobs/355795-practice-support-manager?src=rec' rel='nofollow'>Practice Support Manager</a></div><div><a href='https://angel.co/opencare/jobs/355795-practice-support-manager?src=rec' rel='nofollow'>Opencare</a></div><div>Toronto</div></div></div><div><div><div><a href='https://angel.co/govanhack/jobs/330683-technical-recruiter-east-canada-market?src=rec' rel='nofollow'></a></div><div><a href='https://angel.co/govanhack/jobs/330683-technical-recruiter-east-canada-market?src=rec' rel='nofollow'>Technical Recruiter - East Canad...</a></div><div><a href='https://angel.co/govanhack/jobs/330683-technical-recruiter-east-canada-market?src=rec' rel='nofollow'>VanHack</a></div><div>Toronto, Montreal, Waterloo</div></div></div></div></div></div><div><div><div><div><h3>What We're Building</h3></div><div><div><p>ConsenSys is a blockchain venture production studio building decentralized applications, mostly on Ethereum. We are currently building foundational tools for emerging business models in the cryptocurrency or Bitcoin 2.0 space. These tools will be packaged into separate ventures that are individually funded and skinned for different business niches.</p><p>ConsenSys is presently comprised of a number of core personnel — some of whom are based in New York City, but several are in other cities around the world — who are focussed on the identification, acquisition, and development of talent and projects, in addition to the development of our own internal projects and some focus on consulting work.</p><p>ConsenSys spawns, coordinates, incubates and accelerates single purpose vehicles (SPVs) through internal development, acquisitions, investments, or the formation of joint ventures.</p></div></div><div><div><div><div><div></div><div>Hiring in <span>Brooklyn</span>, <span>San Francisco</span>, <span>Toronto</span>, Remote OK</div><div></div></div><div><div></div><div>501-1000 Employees</div><div></div></div><div><div></div><span>Blockchains</span></div><div><div></div><a href='http://twitter.com/@ConsenSys' rel='nofollow'>@ConsenSys</a></div><div><div></div><a href='https://medium.com/@ConsenSys' rel='nofollow'>https://medium.com/@ConsenSys</a></div><div><div></div><a href='http://ConsenSys.net' rel='nofollow'>ConsenSys.net</a></div></div></div></div></div></div></div><div><div><div><h3>Other Jobs at ConsenSys</h3><ul><li><div>Software Engineering Jobs</div><div><div><div><div><a href='https://angel.co/consensys/jobs/203793-security-engineer-lead-smart-contracts' rel='nofollow'>Security Engineer / Lead - Smart Contracts</a><div>Brooklyn·Full Time<span></span><span>·$90K – $120K · 0.01% – 0.01%</span></div></div><div><div><div><div><div><a rel='nofollow'><span></span>Applied</a></div></div><div></div><div><span>Apply</span><div><div></div><div></div><div><div><div><div>Add a message to ConsenSys</div>Apply<div></div></div></div></div></div></div><div></div></div></div></div></div></div><div><div><div><a href='https://angel.co/consensys/jobs/344978-support-engineer' rel='nofollow'>Support Engineer</a><div>Boston·Full Time<span></span><span>·$70K – $90K · 0.0% – 0.01%</span></div></div><div><div><div><div><div><a rel='nofollow'><span></span>Applied</a></div></div><div></div><div><span>Apply</span><div><div></div><div></div><div><div><div><div>Add a message to ConsenSys</div>Apply<div></div></div></div></div></div></div><div></div></div></div></div></div></div><div><div><div><a href='https://angel.co/consensys/jobs/345709-lead-quality-assurance-balanc3' rel='nofollow'>Lead Quality Assurance (Balanc3)</a><div>Brooklyn·Full Time<span></span><span>·$100K – $150K · No Equity</span></div></div><div><div><div><div><div><a rel='nofollow'><span></span>Applied</a></div></div><div></div><div><span>Apply</span><div><div></div><div></div><div><div><div><div>Add a message to ConsenSys</div>Apply<div></div></div></div></div></div></div><div></div></div></div></div></div></div><div><div><div><a href='https://angel.co/consensys/jobs/345711-lead-backend-engineer-balanc3' rel='nofollow'>Lead Backend Engineer (Balanc3)</a><div>Brooklyn·Full Time<span></span><span>·$110K – $170K · No Equity</span></div></div><div><div><div><div><div><a rel='nofollow'><span></span>Applied</a></div></div><div></div><div><span>Apply</span><div><div></div><div></div><div><div><div><div>Add a message to ConsenSys</div>Apply<div></div></div></div></div></div></div><div></div></div></div></div></div></div><div><div><div><a href='https://angel.co/consensys/jobs/351437-backend-engineer' rel='nofollow'>Backend Engineer</a><div>Brooklyn·Full Time<span></span><span>·$100K – $180K · 0.001% – 1.0%</span></div></div><div><div><div><div><div><a rel='nofollow'><span></span>Applied</a></div></div><div></div><div><span>Apply</span><div><div></div><div></div><div><div><div><div>Add a message to ConsenSys</div>Apply<div></div></div></div></div></div></div><div></div></div></div></div></div></div><div><div><div><a href='https://angel.co/consensys/jobs/369513-front-end-developer-marketing' rel='nofollow'>Front End Developer (Marketing)</a><div>Brooklyn, San Francisco·Full Time<span></span><span>·$90K – $120K · No Equity</span></div></div><div><div><div><div><div><a rel='nofollow'><span></span>Applied</a></div></div><div></div><div><span>Apply</span><div><div></div><div></div><div><div><div><div>Add a message to ConsenSys</div>Apply<div></div></div></div></div></div></div><div></div></div></div></div></div></div><div><div><div><a href='https://angel.co/consensys/jobs/376027-front-end-developer' rel='nofollow'>Front End Developer</a><div>Remote, Brooklyn·Full Time<span></span><span>·$90K – $120K · 0.01% – 0.01%</span></div></div><div><div><div><div><div><a rel='nofollow'><span></span>Applied</a></div></div><div></div><div><span>Apply</span><div><div></div><div></div><div><div><div><div>Add a message to ConsenSys</div>Apply<div></div></div></div></div></div></div><div></div></div></div></div></div></div><div><div><div><a href='https://angel.co/consensys/jobs/376029-senior-full-stack-developer' rel='nofollow'>Senior Full Stack Developer</a><div>Remote, Brooklyn·Full Time<span></span><span>·$100K – $130K · 0.01% – 0.01%</span></div></div><div><div><div><div><div><a rel='nofollow'><span></span>Applied</a></div></div><div></div><div><span>Apply</span><div><div></div><div></div><div><div><div><div>Add a message to ConsenSys</div>Apply<div></div></div></div></div></div></div><div></div></div></div></div></div></div><div><div><div><a href='https://angel.co/consensys/jobs/385210-software-quality-assurance-qa-lead' rel='nofollow'>Software Quality Assurance (QA) Lead</a><div>Singapore, Singapore·Full Time<span></span><span>·$90K – $120K · No Equity</span></div></div><div><div><div><div><div><a rel='nofollow'><span></span>Applied</a></div></div><div></div><div><span>Apply</span><div><div></div><div></div><div><div><div><div>Add a message to ConsenSys</div>Apply<div></div></div></div></div></div></div><div></div></div></div></div></div></div><div><div><div><a href='https://angel.co/consensys/jobs/388019-blockchain-protocol-engineer' rel='nofollow'>Blockchain Protocol Engineer</a><div>Brooklyn·Full Time<span></span><span>·$100K – $180K · No Equity</span></div></div><div><div><div><div><div><a rel='nofollow'><span></span>Applied</a></div></div><div></div><div><span>Apply</span><div><div></div><div></div><div><div><div><div>Add a message to ConsenSys</div>Apply<div></div></div></div></div></div></div><div></div></div></div></div></div></div></div><div></div></li><li><div>Engineering Jobs</div><div><div><div><div><a href='https://angel.co/consensys/jobs/348033-lead-network-operations-engineer' rel='nofollow'>Lead Network Operations Engineer</a><div>Remote, Boston·Full Time<span></span><span>·$90K – $115K · 0.001% – 0.001%</span></div></div><div><div><div><div><div><a rel='nofollow'><span></span>Applied</a></div></div><div></div><div><span>Apply</span><div><div></div><div></div><div><div><div><div>Add a message to ConsenSys</div>Apply<div></div></div></div></div></div></div><div></div></div></div></div></div></div></div><div></div></li><li><div>Marketing Jobs</div><div><div><div><div><a href='https://angel.co/consensys/jobs/332062-events-manager' rel='nofollow'>Events Manager</a><div>Toronto·Full Time<span></span><span>·$75K – $83K · 0.01% – 0.01%</span></div></div><div><div><div><div><div><a rel='nofollow'><span></span>Applied</a></div></div><div></div><div><span>Apply</span><div><div></div><div></div><div><div><div><div>Add a message to ConsenSys</div>Apply<div></div></div></div></div></div></div><div></div></div></div></div></div></div></div><div></div></li><li><div>Operations Jobs</div><div><div><div><div><a href='https://angel.co/consensys/jobs/231931-human-resources-and-recruiting-coordinator' rel='nofollow'>Human Resources and Recruiting Coordinator</a><div>Brooklyn·Full Time<span></span><span>·$50K – $55K · 0.01% – 0.01%</span></div></div><div><div><div><div><div><a rel='nofollow'><span></span>Applied</a></div></div><div></div><div><span>Apply</span><div><div></div><div></div><div><div><div><div>Add a message to ConsenSys</div>Apply<div></div></div></div></div></div></div><div></div></div></div></div></div></div><div><div><div><a href='https://angel.co/consensys/jobs/345614-network-operations-engineer-customer-success' rel='nofollow'>Network Operations Engineer (Customer Success)</a><div>Boston·Full Time<span></span><span>·$40K – $50K · 0.01% – 0.01%</span></div></div><div><div><div><div><div><a rel='nofollow'><span></span>Applied</a></div></div><div></div><div><span>Apply</span><div><div></div><div></div><div><div><div><div>Add a message to ConsenSys</div>Apply<div></div></div></div></div></div></div><div></div></div></div></div></div></div><div><div><div><a href='https://angel.co/consensys/jobs/366882-learning-development-lead' rel='nofollow'>Learning &amp; Development Lead</a><div>Brooklyn·Full Time<span></span><span>·$180K – $190K · 0.001% – 0.001%</span></div></div><div><div><div><div><div><a rel='nofollow'><span></span>Applied</a></div></div><div></div><div><span>Apply</span><div><div></div><div></div><div><div><div><div>Add a message to ConsenSys</div>Apply<div></div></div></div></div></div></div><div></div></div></div></div></div></div><div><div><div><a href='https://angel.co/consensys/jobs/367843-self-managing-systems-designer-facilitator' rel='nofollow'>Self-Managing Systems Designer &amp; Facilitator</a><div>Brooklyn·Full Time<span></span><span>·$135K – $145K · 0.001% – 0.001%</span></div></div><div><div><div><div><div><a rel='nofollow'><span></span>Applied</a></div></div><div></div><div><span>Apply</span><div><div></div><div></div><div><div><div><div>Add a message to ConsenSys</div>Apply<div></div></div></div></div></div></div><div></div></div></div></div></div></div><div><div><div><a href='https://angel.co/consensys/jobs/367859-self-management-curriculum-designer-content-creator' rel='nofollow'>Self-Management Curriculum Designer/Content Creator</a><div>Brooklyn, Remote·Full Time<span></span><span>·$50K – $60K · 0.001% – 0.001%</span></div></div><div><div><div><div><div><a rel='nofollow'><span></span>Applied</a></div></div><div></div><div><span>Apply</span><div><div></div><div></div><div><div><div><div>Add a message to ConsenSys</div>Apply<div></div></div></div></div></div></div><div></div></div></div></div></div></div><div><div><div><a href='https://angel.co/consensys/jobs/376369-customer-success-manager' rel='nofollow'>Customer Success Manager</a><div>Boston, Romania, Remote·Full Time<span></span><span>·$70K – $80K · 0.01% – 0.01%</span></div></div><div><div><div><div><div><a rel='nofollow'><span></span>Applied</a></div></div><div></div><div><span>Apply</span><div><div></div><div></div><div><div><div><div>Add a message to ConsenSys</div>Apply<div></div></div></div></div></div></div><div></div></div></div></div></div></div></div><div></div></li><li><div>Other Jobs</div><div><div><div><div><a href='https://angel.co/consensys/jobs/329943-acquisitions-and-asset-management-analyst-pangea' rel='nofollow'>Acquisitions and Asset Management Analyst (Pangea)</a><div>Brooklyn·Full Time<span></span><span>·$75K – $90K · 0.01% – 0.01%</span></div></div><div><div><div><div><div><a rel='nofollow'><span></span>Applied</a></div></div><div></div><div><span>Apply</span><div><div></div><div></div><div><div><div><div>Add a message to ConsenSys</div>Apply<div></div></div></div></div></div></div><div></div></div></div></div></div></div><div><div><div><a href='https://angel.co/consensys/jobs/366867-business-operations-associate-global-operations' rel='nofollow'>Business Operations Associate, Global Operations</a><div>Brooklyn·Full Time<span></span><span>·$70K – $80K · 0.001% – 0.001%</span></div></div><div><div><div><div><div><a rel='nofollow'><span></span>Applied</a></div></div><div></div><div><span>Apply</span><div><div></div><div></div><div><div><div><div>Add a message to ConsenSys</div>Apply<div></div></div></div></div></div></div><div></div></div></div></div></div></div><div><div><div><a href='https://angel.co/consensys/jobs/385211-business-analyst-strategy-consultant' rel='nofollow'>Business Analyst/Strategy Consultant</a><div>Singapore, Singapore·Full Time<span></span><span>·$90K – $110K · No Equity</span></div></div><div><div><div><div><div><a rel='nofollow'><span></span>Applied</a></div></div><div></div><div><span>Apply</span><div><div></div><div></div><div><div><div><div>Add a message to ConsenSys</div>Apply<div></div></div></div></div></div></div><div></div></div></div></div></div></div></div><div></div></li></ul></div></div></div><div><div><div><h3>ConsenSys Team</h3><div><div><div><div><div><a href='https://angel.co/joseph-lubin-1' rel='nofollow'></a></div><div><div><a href='https://angel.co/joseph-lubin-1' rel='nofollow'>Joseph Lubin</a></div></div></div><div><div><a href='https://angel.co/ash-hogan' rel='nofollow'></a></div><div><div><a href='https://angel.co/ash-hogan' rel='nofollow'>Ash Hogan</a><span>,</span></div><div>Global Talent Acquisition Leader, Solutions at ConsenSys | Founder at emplyd | Advisor</div></div></div><div><div><a href='https://angel.co/ash-egan' rel='nofollow'></a></div><div><div><a href='https://angel.co/ash-egan' rel='nofollow'>Ash Egan</a><span>,</span></div><div>VC <a href='https://angel.co/consensys' title=&quot;ConsenSys&quot; rel='nofollow'><span>@</span><span>ConsenSys</span></a> </div></div></div><div><div><a href='https://angel.co/kendall-cole-1' rel='nofollow'></a></div><div><div><a href='https://angel.co/kendall-cole-1' rel='nofollow'>Kendall Cole</a><span>,</span></div><div>Building kauri.io <a href='https://angel.co/consensys' title=&quot;ConsenSys&quot; rel='nofollow'><span>@</span><span>ConsenSys</span></a> . <a href='https://angel.co/entrepreneur-first' title=&quot;Entrepreneur First&quot; rel='nofollow'><span>@</span><span>Entrepreneur First</span></a> EF 7. Co-Founder <a href='https://angel.co/oilfront' title=&quot;OilFront&quot; rel='nofollow'><span>@</span><span>OilFront</span></a> <a href='https://angel.co/jobfire' title=&quot;EntryWire&quot; rel='nofollow'><span>@</span><span>EntryWire</span></a> . <a href='https://angel.co/startupchile' title=&quot;Start-Up Chile&quot; rel='nofollow'><span>@</span><span>Start-Up Chile</span></a>  Gen 13. Former engineer <a href='https://angel.co/unbabel' title=&quot;Unbabel&quot; rel='nofollow'><span>@</span><span>Unbabel</span></a>  and <a href='https://angel.co/veenome' title=&quot;Veenome&quot; rel='nofollow'><span>@</span><span>Veenome</span></a>. UVA 2013</div></div></div><div><div><a href='https://angel.co/eric-morrow' rel='nofollow'></a></div><div><div><a href='https://angel.co/eric-morrow' rel='nofollow'>Eric Morrow</a><span>,</span></div><div>Digital Marketing specialist, focused on helping startups attract customers.</div></div></div><div><div><a href='https://angel.co/juanllanos' rel='nofollow'></a></div><div><div><a href='https://angel.co/juanllanos' rel='nofollow'>Juan Llanos</a><span>,</span></div><div>Founder <a href='https://angel.co/unidos-financial-services' title=&quot;Unidos Financial Services&quot; rel='nofollow'><span>@</span><span>Unidos Financial Services</span></a> • Studied at <a href='https://angel.co/universidad-de-palermo' rel='nofollow'><span>@</span><span>Universidad de Palermo</span></a>, <a href='https://angel.co/virginia-commonwealth-university' rel='nofollow'><span>@</span><span>Virginia Commonwealth University</span></a></div></div></div></div></div></div><div></div><div><span>See More</span><span></span></div><div></div></div></div></div><div><div><div><div><div>ConsenSys is one of 26,103 startups hiring on AngelList</div><div></div></div><div><div><span>Browse All Startup Jobs</span><a href='https://angel.co/recruiting/signup?src=job-showcase' rel='nofollow'>Post a Job</a></div></div><div><span>Help</span>·<span>Terms</span>·<span>Jobs by location</span><span>Problem?<span>Report this company</span></span></div></div></div></div></div><div></div>"
  },
  {
    "id": "vzuX3tKjQSWGy7_9iL4BAQ",
    "url": "https://weworkremotely.com/remote-jobs/clevertech-talent-acquisition-manager",
    "title": "Clevertech: Talent Acquisition Manager",
    "tags": [
      "DBG:surround``3N( OR(feasibl,OR(consid,consider),option,occas,opportun,possibl,abil), OR(3N(remot, work),telecommut,2N(work,home)) ) NOT OR(regularli, abracadabra)",
      "DBG:surround``headquart 3N remot",
      "DBG:surround``remot 3N ( OR(employe,develop,engin,team,role,employment,workmat) OR compani OR worldwide)",
      "DBG_TECH1:k/t/w:go/go/3",
      "DBG_TECH1:techWeightMap:{python=0, other=0, dotnet=0, c=0, mobile=0, go=3, nodejs=0, bigdata-ml=0, ruby=0, apple=0, java=0, gamedev=0, php=0, embedded=0, frontend=0}",
      "REMOTE1/100",
      "TECH1/go",
      "TITLE1/HR",
      "TZ/unknown"
    ],
    "tagsNames1": [],
    "tagsNames2": [
      "go"
    ],
    "hiringOrganization": {
      "name": "UNSET",
      "sameAs": "UNSET"
    },
    "salary": {
      "currency": "UNSET",
      "minValue": 0,
      "maxValue": 0,
      "info": "",
      "unit": "UNSET",
      "isEquity": false
    },
    "employmentType": "UNSET",
    "published": "Jul 26, 2018 8:57:22 PM",
    "validThrough": "Jan 1, 1970 1:00:00 AM",
    "content": "<h2>Talent Acquisition Manager</h2><span>Company: Clevertech<br></span><span>Headquarters: Remote<br></span><span>https://www.clevertech.biz/<br><br></span>  <div>    <div><h3>DESCRIPTION</h3></div><div>Clevertech is currently seeking a Manager of Talent Acquisition to join our Recruiting team. This is an exciting opportunity for anyone interested in a career in People Operations within an organization that will provide opportunities for growth. This position will be part of the strategic management responsible for Talent Acquisition. The Manager will work with recruiting/hiring managers to fully understand their needs and generate candidate leads utilizing passive resources and effectively screening candidates. This highly attractive position will possess a flexible work arrangement with the ability to work from home.<br></div><div><h3>REQUIREMENTS</h3></div><ul><li>5+ years recruiting experience</li><li>Excellent interpersonal and communication skills</li><li>Demonstrable experience in tech industry recruiting and sales recruiting</li><li>Extensive knowledge of applicant tracking software programs</li><li>Familiarity with online job hunting websites</li><li>Ability to deliver results with little supervision, and to effectively manage multiple projects and candidates</li><li>Proven ability to build and maintain candidate pipelines, including using relationship management techniques, that yield high quality candidates for short and long term hiring needs *Evidence of building candidate relationships and managing a network of talent Superb customer focus, attention to detail, and organization skills</li></ul><div><h3>BENEFITS</h3><h5>Own Your Time</h5></div><div>We are a completely remote team. That means we have a large amount of trust and a lot of flexibility. World travellers, young parents, nature lovers, and commute avoiders love working here. We also will pay for a co-working space in case you feel like working outside of your normal setting.</div><div><br></div><div><h5>Recharge Time</h5></div><div>We insist that you take recharge time. We are closed for major holidays and then require that you take at least two weeks a year to refresh.</div><div><br></div><div><h5>Care For Yourself</h5></div><div>You’ll receive a health/wellness stipend that can go towards covering medical insurance, dental insurance, or joining a gym!</div><div><br></div><div><h5>Focused Work</h5></div><div>You will work together on a dedicated team with your eye on one finish line at a time. Our teams are nimble and agile, and cover the technical range you would expect in world class product delivery teams.</div><div><br></div><div><h5>Learn at your edges</h5></div><div>We believe in learning and provide unique programs that improve your tech skills, leadership skills and even challenge you in personal development. CleverFridays, guest speakers, mentorship opportunities and in-depth industry exposure are all on offer here. And of course, if you speak at a tech conference, we cover all expenses.</div><div><br></div><div><h5>Clevertech Swag</h5></div><div>And keep your eye on the mail - we send out swag everywhere in the world and there are celebratory pictures of Clevertech socks, hoodies, and mugs all over slack.</div><div><br></div>  </div>  <div>    <h4>Apply for this position</h4>    <p><a href='https://hire.clevertech.biz/job/563963b0f3c394067e18f79f' rel='nofollow'>https://hire.clevertech.biz/job/563963b0f3c394067e18f79f</a></p>  </div>"
  },
  {
    "id": "hQVnSk4TQWqADCgkCWfwew",
    "url": "https://angel.co/consumeracquisition-com/jobs/114999-facebook-user-acquisition",
    "title": "Facebook User Acquisition",
    "tags": [
      "Austin",
      "DBG:surround``remot W OR(contractor,assist,ok)",
      "DBG_TECH1:k/t/w:coffeescript/frontend/1",
      "DBG_TECH1:k/t/w:coffeescript/nodejs/1",
      "DBG_TECH1:techWeightMap:{python=0, other=0, dotnet=0, c=0, mobile=0, go=0, nodejs=1, bigdata-ml=0, ruby=0, apple=0, java=0, gamedev=0, php=0, embedded=0, frontend=1}",
      "Facebook Advertising",
      "Full Time",
      "Los Angeles",
      "Marketing",
      "REMOTE1/100",
      "Remote OK",
      "San Francisco",
      "TECH1/frontend",
      "TECH1/nodejs",
      "TITLE1/HR",
      "TZ/unknown"
    ],
    "tagsNames1": [],
    "tagsNames2": [
      "frontend",
      "nodejs"
    ],
    "hiringOrganization": {
      "name": "UNSET",
      "sameAs": "UNSET"
    },
    "salary": {
      "currency": "USD",
      "minValue": 80000,
      "maxValue": 160000,
      "info": "No Equity",
      "unit": "YEAR",
      "isEquity": false
    },
    "employmentType": "UNSET",
    "published": "Jul 20, 2018 6:26:18 PM",
    "validThrough": "Jan 1, 1970 1:00:00 AM",
    "content": "Facebook User Acquisition Job at ConsumerAcquisition.com - AngelList<div><div><div><div><div><div><a title=&quot;ConsumerAcquisition.com&quot; href='https://angel.co/consumeracquisition-com/jobs' rel='nofollow'></a></div><div></div><ul><li><span>ConsumerAcquisiti...</span></li><li><span>Product</span></li><li><span>Jobs</span></li><li><span>Team</span></li></ul><div><div><div><div><div><a rel='nofollow'><span></span>Applied</a></div></div><div></div><div><span>Apply Now</span><div><div></div><div></div><div><div><div><div>Add a message to ConsumerAcquisition.com</div>Apply<div></div></div></div></div></div></div><div></div></div></div><div><div><span>Share</span></div></div></div></div></div></div></div><div><div><div></div></div><div><div><div><a title=&quot;ConsumerAcquisition.com&quot; href='https://angel.co/consumeracquisition-com' rel='nofollow'></a></div><div><h2>Facebook User Acquisition at ConsumerAcquisition.com</h2><div>San Francisco, Austin, Los Angeles, Remote · Full Time</div><div><div><div><div><div><a rel='nofollow'><span></span>Applied</a></div></div><div></div><div><span>Apply to ConsumerAcquisition.com</span><div><div></div><div></div><div><div><div><div>Add a message to ConsumerAcquisition.com</div>Apply<div></div></div></div></div></div></div><div></div></div></div></div></div></div><div></div></div></div><div><div><div><h3>Job Description</h3></div><div><div><p>Are you passionate about Facebook advertising and user acquisition? Do you want to deliver world-class performance to clients while having autonomy and personal freedom?  If so, then we want to work with you!</p><p>We are looking for entrepreneurial individuals who are seeking an analytically challenging and strategic role with a fast-growing startup. </p><p>Manage all aspects of Facebook and Instagram advertising campaigns using our proprietary software, AdRules. <br>• Oversee execution and optimization of Facebook advertising campaigns to exceed clients’ goals across many verticals.<br>• Plan, manage, optimize, and report on paid social media campaigns.<br>• Become an expert in Facebook advertising and the AdRules platform.<br>• Write ad copy and work with graphic designers to optimize images.</p><p>Responsibilities:<br>• Manage all aspects of Facebook and Instagram advertising: build ads, analyze data, optimize continuously and manage creative testing.<br>• Develop strategies to exceed clients’ performance goals.<br>• Create images in Photoshop (or manage external designers) and write ad copy to optimize performance.<br>• Analyze your ad spend and use the data to formulate your strategy.<br>• Optimize ads for efficiency based on performance data using our AdRules platform.<br>• Develop client-facing skills on weekly calls, deliver strategic insights and daily summaries.</p><p>Requirements:<br>• Strong analytics, quantitative and problem-solving skills; ability to analyze raw data, draw conclusions, and develop actionable recommendations.<br>• BA / BS / MBA or 2+ years’ experience in high-scale, hands-on performance marketing role with Facebook Ads and User Acquisition.<br>• Experience in performance marketing, online advertising, media buying, lead generation or consulting.<br>• Strong understanding of ads metrics (CPI, CTR, CPC, CPM, CPA, ROAS, ROI, LTV).<br>• Advanced knowledge of Excel.</p><p>Benefits:<br>• Highly competitive salary.<br>• Work from home flexibility.<br>• Uncapped vacation and sick time.</p></div></div><div><div>Skills</div><div>Facebook Advertising</div><div>Compensation</div><div>$80K–$160K<br>No Equity</div><div>Visa Sponsorship</div><div>Not available</div></div><div><div><div><div><div><a rel='nofollow'><span></span>Applied</a></div></div><div></div><div><span>Apply Now</span><div><div></div><div></div><div><div><div><div>Add a message to ConsumerAcquisition.com</div>Apply<div></div></div></div></div></div></div><div></div></div></div></div></div></div><div><div><div><div><h4>People also viewed</h4></div><div><div><div><a href='https://angel.co/knack/jobs/63239-marketing-growth-hacker?src=rec' rel='nofollow'></a></div><div><a href='https://angel.co/knack/jobs/63239-marketing-growth-hacker?src=rec' rel='nofollow'>Marketing/Growth Hacker</a></div><div><a href='https://angel.co/knack/jobs/63239-marketing-growth-hacker?src=rec' rel='nofollow'>Knack</a></div><div>Earth, United States</div></div></div><div><div><div><a href='https://angel.co/theauthenticcompany/jobs/271740-growth-hacker?src=rec' rel='nofollow'></a></div><div><a href='https://angel.co/theauthenticcompany/jobs/271740-growth-hacker?src=rec' rel='nofollow'>Growth Hacker</a></div><div><a href='https://angel.co/theauthenticcompany/jobs/271740-growth-hacker?src=rec' rel='nofollow'>The Authentic Company</a></div><div>Chicago</div></div></div><div><div><div><a href='https://angel.co/coffee-meets-bagel/jobs/289429-senior-user-acquisition-manager?src=rec' rel='nofollow'></a></div><div><a href='https://angel.co/coffee-meets-bagel/jobs/289429-senior-user-acquisition-manager?src=rec' rel='nofollow'>Senior User Acquisition Manager</a></div><div><a href='https://angel.co/coffee-meets-bagel/jobs/289429-senior-user-acquisition-manager?src=rec' rel='nofollow'>Coffee Meets Bagel</a></div><div>San Francisco</div></div></div><div><div><div><a href='https://angel.co/fitivity-2/jobs/354360-chief-marketer-cmo-direct-to-consumer-marketing-at-fitivity?src=rec' rel='nofollow'></a></div><div><a href='https://angel.co/fitivity-2/jobs/354360-chief-marketer-cmo-direct-to-consumer-marketing-at-fitivity?src=rec' rel='nofollow'>Chief Marketer, CMO, Direct-to-C...</a></div><div><a href='https://angel.co/fitivity-2/jobs/354360-chief-marketer-cmo-direct-to-consumer-marketing-at-fitivity?src=rec' rel='nofollow'>Fitivity</a></div><div>Boston</div></div></div><div><div><div><a href='https://angel.co/simplepractice/jobs/293480-director-of-marketing?src=rec' rel='nofollow'></a></div><div><a href='https://angel.co/simplepractice/jobs/293480-director-of-marketing?src=rec' rel='nofollow'>Director of Marketing</a></div><div><a href='https://angel.co/simplepractice/jobs/293480-director-of-marketing?src=rec' rel='nofollow'>SimplePractice</a></div><div>Santa Monica</div></div></div><div><div><div><a href='https://angel.co/forkable/jobs/110183-awesome-people?src=rec' rel='nofollow'></a></div><div><a href='https://angel.co/forkable/jobs/110183-awesome-people?src=rec' rel='nofollow'>Awesome People</a></div><div><a href='https://angel.co/forkable/jobs/110183-awesome-people?src=rec' rel='nofollow'>Forkable</a></div><div>San Francisco</div></div></div><div><div><div><a href='https://angel.co/meshify/jobs/59633-chief-marketing-officer?src=rec' rel='nofollow'></a></div><div><a href='https://angel.co/meshify/jobs/59633-chief-marketing-officer?src=rec' rel='nofollow'>Chief Marketing Officer</a></div><div><a href='https://angel.co/meshify/jobs/59633-chief-marketing-officer?src=rec' rel='nofollow'>Meshify</a></div><div>Austin</div></div></div><div><div><div><a href='https://angel.co/creative-market/jobs/230823-product-manager-growth?src=rec' rel='nofollow'></a></div><div><a href='https://angel.co/creative-market/jobs/230823-product-manager-growth?src=rec' rel='nofollow'>Product Manager, Growth</a></div><div><a href='https://angel.co/creative-market/jobs/230823-product-manager-growth?src=rec' rel='nofollow'>Creative Market</a></div><div>San Francisco, United States</div></div></div><div><div><div><a href='https://angel.co/recruitingawesome/jobs/356925-remote-inbound-paid-social-marketing-manager-remote?src=rec' rel='nofollow'></a></div><div><a href='https://angel.co/recruitingawesome/jobs/356925-remote-inbound-paid-social-marketing-manager-remote?src=rec' rel='nofollow'>Remote Inbound Paid Social Marke...</a></div><div><a href='https://angel.co/recruitingawesome/jobs/356925-remote-inbound-paid-social-marketing-manager-remote?src=rec' rel='nofollow'>#RecruitingAwesome</a></div><div>Orlando</div></div></div></div></div></div><div><div><div><div><h3>What We're Building</h3></div><div><div><p>Founded in 2013, Consumer Acquisition offers the first end-to-end user acquisition solution with managed services, a creative marketplace for Facebook and Google ad creation and an AI-powered campaign automation platform with an action-based reporting. </p><p>We’ve created over 250,000 videos and acquired over 150 million app installs and leads for Glu Mobile, Lucktastic, PlayStudios, Nordcurrent, Checkout51, Blue Apron, Ford, PlayDots, EBATES and many more. We have a special CMO in-a-box startup package designed for VC-backed, pre-A Round companies.</p><p><a href='mailto:Sales@ConsumerAcquisition.com' rel='nofollow'>Sales@ConsumerAcquisition.com</a></p></div></div><div><div><div><div><div></div><div>Hiring in <span>San Francisco</span>, <span>Austin</span>, <span>Los Angeles</span>, Remote OK</div><div></div></div><div><div></div><div>11-50 Employees</div><div></div></div><div><div></div><a href='http://twitter.com/conacq' rel='nofollow'>@conacq</a></div><div><div></div><a href='http://www.consumeracquisition.com/blog/' rel='nofollow'>http://www.consumeracquisition.com/blog/</a></div><div><div></div><a href='http://www.ConsumerAcquisition.com' rel='nofollow'>ConsumerAcquisition.com</a></div></div></div></div></div></div></div><div><div><div><div><div><div><a href='https://d2gn4xht817m0g.cloudfront.net/p/product_screenshots/images/original/000/779/878/779878-c5d920bd9e4b79bd7af31b4922dbfadd70e130b0.png?1484669184' rel='nofollow'></a></div></div></div><div><div><div><a href='https://d2gn4xht817m0g.cloudfront.net/p/product_screenshots/images/original/000/779/879/779879-5d4351e2a166783816e79b1bd4bd4eb3e2a37462.png?1484669284' rel='nofollow'></a></div></div></div><div><div><div><a href='https://d2gn4xht817m0g.cloudfront.net/p/product_screenshots/images/original/000/779/880/779880-841a450a3f9c4ab4f00a0baea9ca068e38647346.png?1484669305' rel='nofollow'></a></div></div></div><div><div><div><a href='https://d2gn4xht817m0g.cloudfront.net/p/product_screenshots/images/original/000/806/832/806832-a20be29ee3a69b29cc0f5ac691be6e15422a91ad.jpg?1493051626' rel='nofollow'></a></div></div></div><div><div><div><a href='https://d2gn4xht817m0g.cloudfront.net/p/product_screenshots/images/original/000/806/833/806833-49088923f470f9bbe70ade1a36edb58909fe6c1d.jpg?1493051694' rel='nofollow'></a></div></div></div><div><div><div><a href='https://d2gn4xht817m0g.cloudfront.net/p/product_screenshots/images/original/000/843/995/843995-7ca572d9228f171ecb75218d37ae6a672504592b.jpg?1510593138' rel='nofollow'></a></div></div></div><div><div><div><a href='https://angel.co/projects/578116-creative-marketplace-for-facebook-advertisers-now-available-to-the-public?src=startup_profile' rel='nofollow'></a></div><div><div><a title=&quot;ConsumerAcquisition.com&quot; href='https://angel.co/consumeracquisition-com' rel='nofollow'></a></div><div><div><a href='https://angel.co/projects/578116-creative-marketplace-for-facebook-advertisers-now-available-to-the-public?src=startup_profile' rel='nofollow'>Creative Marketplace for Facebook advertisers now available to the public!</a></div>Creative Marketplace for Facebook advertisers </div><div></div></div></div></div><div><div><div><a href='https://angel.co/projects/208305-adrules?src=startup_profile' rel='nofollow'></a></div><div><div><a title=&quot;ConsumerAcquisition.com&quot; href='https://angel.co/consumeracquisition-com' rel='nofollow'></a></div><div><div><a href='https://angel.co/projects/208305-adrules?src=startup_profile' rel='nofollow'>AdRules</a></div>Designed for Mobile App Advertising on Facebook &amp; Instagram</div><div></div></div></div></div><div><div><div><a href='https://angel.co/projects/450466-free-reporting-consumeracquisition-com?src=startup_profile' rel='nofollow'></a></div><div><div><a title=&quot;ConsumerAcquisition.com&quot; href='https://angel.co/consumeracquisition-com' rel='nofollow'></a></div><div><div><a href='https://angel.co/projects/450466-free-reporting-consumeracquisition-com?src=startup_profile' rel='nofollow'>Free Reporting - ConsumerAcquisition.com</a></div>Free Advanced Reporting for Facebook Advertisers</div><div></div></div></div></div><div><div><div><a href='https://angel.co/projects/518558-advertisers-consumeracquisition-com?src=startup_profile' rel='nofollow'></a></div><div><div><a title=&quot;ConsumerAcquisition.com&quot; href='https://angel.co/consumeracquisition-com' rel='nofollow'></a></div><div><div><a href='https://angel.co/projects/518558-advertisers-consumeracquisition-com?src=startup_profile' rel='nofollow'>Advertisers | ConsumerAcquisition.com</a></div>Creative Marketplace for Facebook Advertising</div><div></div></div></div></div></div><div><div><div><div></div><div>Add testimonials, product launches, and photos that highlight your company</div>Add Highlight</div></div></div><div></div></div></div><div><div><div><h3>Other Jobs at ConsumerAcquisition.com</h3><ul><li><div>Software Engineering Jobs</div><div><div><div><div><a href='https://angel.co/consumeracquisition-com/jobs/96191-senior-engineer' rel='nofollow'>Senior Engineer</a><div>San Francisco·Full Time<span></span><span>·$100K – $175K · No Equity</span></div></div><div><div><div><div><div><a rel='nofollow'><span></span>Applied</a></div></div><div></div><div><span>Apply</span><div><div></div><div></div><div><div><div><div>Add a message to ConsumerAcquisition.com</div>Apply<div></div></div></div></div></div></div><div></div></div></div></div></div></div></div><div></div></li></ul></div></div></div><div><div><div><h3>ConsumerAcquisition.com Team</h3><div><div><div><div><div><a href='https://angel.co/brianbowman' rel='nofollow'></a></div><div><div><a href='https://angel.co/brianbowman' rel='nofollow'>Brian Bowman</a><span>,</span></div><div>CEO <a href='https://angel.co/consumeracquisition-com' title=&quot;ConsumerAcquisition.com&quot; rel='nofollow'><span>@</span><span>ConsumerAcquisition.com</span></a>, Facebook End-To-End User Acquisition For Facebook Advertising, Worked at <a href='https://angel.co/match-com' title=&quot;Match.com&quot; rel='nofollow'><span>@</span><span>Match.com</span></a>, <a href='https://angel.co/yahoo' title=&quot;Yahoo&quot; rel='nofollow'><span>@</span><span>Yahoo</span></a>,  <a href='https://angel.co/the' title=&quot;THE&quot; rel='nofollow'><span>@</span><span>THE</span></a> Walt Disney Company</div></div></div><div><div><a href='https://angel.co/tom-young-2' rel='nofollow'></a></div><div><div><a href='https://angel.co/tom-young-2' rel='nofollow'>tom young</a></div></div></div><div><div><a href='https://angel.co/brian-kanaga' rel='nofollow'></a></div><div><div><a href='https://angel.co/brian-kanaga' rel='nofollow'>Brian Kanaga</a></div></div></div></div></div></div><div></div></div></div></div><div><div><div><div><div>ConsumerAcquisition.com is one of 26,093 startups hiring on AngelList</div><div></div></div><div><div><span>Browse All Startup Jobs</span><a href='https://angel.co/recruiting/signup?src=job-showcase' rel='nofollow'>Post a Job</a></div></div><div><span>Help</span>·<span>Terms</span>·<span>Jobs by location</span><span>Problem?<span>Report this company</span></span></div></div></div></div></div><div></div>"
  },
  {
    "id": "IV7baVHHTySGL6P8Q1psMA",
    "url": "https://news.ycombinator.com/item?id=17445211",
    "title": "SEEKING FREELANCER Worldwide, REMOTE, near-total flexibility on hours. $70-100/hr. Expert Interviewer at Karat (https://karat.io) Work from ...",
    "tags": [
      "DBG:surround``4W( OR(fulltim,work,talent), anywher)",
      "DBG:surround``seek 2W freelancerescap 4W remot",
      "REMOTE1/100",
      "TECH1/unknown",
      "TITLE1/HR",
      "TZ/unknown"
    ],
    "tagsNames1": [],
    "tagsNames2": [
      "unknown"
    ],
    "hiringOrganization": {
      "name": "UNSET",
      "sameAs": "UNSET"
    },
    "salary": {
      "currency": "UNSET",
      "minValue": 0,
      "maxValue": 0,
      "info": "",
      "unit": "UNSET",
      "isEquity": false
    },
    "employmentType": "UNSET",
    "published": "Jul 2, 2018 10:48:04 PM",
    "validThrough": "Jan 1, 1970 1:00:00 AM",
    "content": "<span>SEEKING FREELANCER<p>Worldwide, REMOTE, near-total flexibility on hours. $70-100/hr. Expert Interviewer at Karat (<a href='https://karat.io' rel='nofollow'>https://karat.io</a>)</p><p>Work from anywhere in the world that has a solid internet connection. Work as much or as little as you want. Work any day, any time of day, any number of hours -- you can do 0 one week, 50 the next week, and back to 0 the next week. Only requirement there is that we want you to roughly average at least 10 hours a week, or else the training/time investment doesn't make as much sense from your end or ours.</p><p>I know the above might sound a little strange, so a bit about the company for context: Karat is a Seattle-based startup that does software engineering interviews on behalf of other companies -- primarily first-round phone screens. Quickly-growing companies can spend a significant fraction of their engineers' time interviewing; we help take the load off. We've done a lot to make the interview experience better for all stakeholders that I could write whole essays about, but suffice it to say that candidates love working with us, clients love working with us, and we're well-funded and growing quickly as a result.</p><p>Because of this quickly-growing demand, we're looking to hire more Expert Interviewers. The ideal candidate is a software engineer with strong written and verbal English skills with at least a few years of professional experience. Interviewing experience would be great, but we spend 25 hours (paid) training you before you even start, so if you're strong technically and love working with people we can usually make it work :) Interviews are conducted over video chat, using a collaborative code editor.</p><p>Some of our interviewers are freelancers who use our scheduling model to backfill hours; others are full timers at top tech companies looking to make some extra cash; others have quit their jobs to work with us full time; some are digital nomads; one of our interviewers is road tripping around North America for a year and a half, doing anywhere from zero to 40 interviews each week depending on where he is and what the weather's like.</p><p>The application form is here: <a href='https://jobs.lever.co/karat/d44ab283-c7c0-4bbd-b8c3-4dc0ced64c86?lever-origin=applied&amp;lever-source=HNWHFL' rel='nofollow'>https://jobs.lever.co/karat/d44ab283-c7c0-4bbd-b8c3-4dc0ced6...</a></p><p>I know it's a pretty unique job, so if you have any questions reply here or email me at josh@karat.io and I'm happy to talk through any of it.<span>              </span></p><div>        <p>                        </p></div></span>"
  },
  {
    "id": "I7Of0n9hQ9SgDmd_5oKvfQ",
    "url": "http://workinstartups.com/job-board/job/70264/talent-coordinator-at-dice/",
    "title": "Talent Coordinator",
    "tags": [
      "DBG:surround``OR(work,oper,anywher,remot) 3W OR(feel,creativ)",
      "REMOTE1/100",
      "TECH1/unknown",
      "TITLE1/HR",
      "TZ/unknown"
    ],
    "tagsNames1": [],
    "tagsNames2": [
      "unknown"
    ],
    "hiringOrganization": {
      "name": "UNSET",
      "sameAs": "UNSET"
    },
    "salary": {
      "currency": "UNSET",
      "minValue": 0,
      "maxValue": 0,
      "info": "",
      "unit": "UNSET",
      "isEquity": false
    },
    "employmentType": "UNSET",
    "published": "Jun 21, 2018 11:42:43 AM",
    "validThrough": "Jan 1, 1970 1:00:00 AM",
    "content": "Since our UK launch in 2014, DICE has become the world's most innovative music discovery and ticketing platform. Fans are able to discover and find tickets to the hottest shows, club nights and festivals on the only live music discovery platform that’s built with the user in mind. Every event is handpicked by a team of show-obsessed experts.<br /><br />DICE GETS FANS IN.<br /><br />Some call it HR, here at DICE we call it the People Team - we're passionate about finding, growing and developing our amazing people at DICE. As a Talent Coordinator, you’ll play a proactive and cross-functional role working with all teams.<br /><br />We’re looking for a Talent Coordinator who will take charge of all our coordination efforts to help scale our awesome teams. We’re recruiting globally across the entire business, spanning from software engineering and UX development through to brand partnerships and account management.<br /><br />We’re on the lookout for a highly organised, adaptable, people person to support our recruitment efforts and expansion. You will be the first point of contact for anyone applying to DICE and responsible for ensuring that all DICE candidates feel valued, and receive an incredible candidate experience from start to finish.<br /><br />Responsibilities:<br />*Effectively coordinating the full lifecycle of interviews for all DICE candidates across teams; ensuring a proactive and positive candidate experience<br />* Supporting the talent partner in ensuring our applicant tracking system is up to date and candidates are updated on next steps<br />* Manage our job adverts for all open positions, including our accounts with tools and platforms and updating our profiles where necessary<br />* Making candidates feel welcomed and providing them with a tour of our offices<br />* Working with our Creative and Branding team to create engaging content for our pages to improve our employee brand and attract quality candidates<br /><br />Requirements:<br />* Demonstrable experience working within a people function role for 1-2 years (recruitment coordinator, HR assistant, etc.)<br />* Excellent communication skills, both written and spoken<br />* Motivated, exceptionally organised and detail oriented<br />* Ability to spin multiple plates - not afraid to take on multiple tasks but know how to prioritise to achieve deadlines<br />* Friendly, open-minded with a positive can-do attitude<br />* High EQ<br />* Creative problem solver<br />* Experienced dealing with sensitive information with the ability to work in a confidential manner<br />* Startup experience (bonus)<br /><br />Benefits:<br />* Competitive salary<br />* Unlimited holiday<br />* Private Healthcare<br />* Mental Health and Wellbeing programmes<br />* Sanctus Coaches<br />* DICE Development Programme<br />* DICE credit to spend on gigs<br />* Regular socials<br />* Free breakfast<br />* We love our HQ in East London check it out &quot;here&quot;:http://www.debeauvoirblock.com/#home"
  },
  {
    "id": "9nBXDpl3R_WTstzcO0fMoA",
    "url": "http://workinstartups.com/job-board/job/69780/internal-recruiter-at-roli/",
    "title": "Internal Recruiter",
    "tags": [
      "DBG:surround``2N(work, remot) 2N OR(option, allow, abl, possibl, permit)",
      "DBG:surround``OR(abl,will,challeng,flexibl,experi,get,prefer) 2W 2N(work,remot)",
      "REMOTE1/50",
      "TECH1/unknown",
      "TITLE1/HR",
      "TZ/unknown"
    ],
    "tagsNames1": [
      "50% remote"
    ],
    "tagsNames2": [
      "unknown"
    ],
    "hiringOrganization": {
      "name": "UNSET",
      "sameAs": "UNSET"
    },
    "salary": {
      "currency": "UNSET",
      "minValue": 0,
      "maxValue": 0,
      "info": "",
      "unit": "UNSET",
      "isEquity": false
    },
    "employmentType": "UNSET",
    "published": "Jun 7, 2018 5:23:03 PM",
    "validThrough": "Jan 1, 1970 1:00:00 AM",
    "content": "&quot;ROLI is not only a learning-rich environment within your own discipline, but other team members<br /><br />often make me question the world in new ways while we're eating lunch.&quot;<br /><br /> - Sarah Kosar, Head of Talent<br /><br />ROLI is looking for an experienced, motivated, and thoughtful Internal Recruiter to join our Talent Team to help us continue to grow our global multidisciplinary team.<br />As a core member of our friendly and effective Talent Team, you will focus on direct sourcing our open and upcoming technical and non-technical positions, building talent pools that convert conversations into excellent candidate, brand and ultimately team member experiences. You will collaborate closely with the Talent Team on a wide range of the Talent Function including sourcing, role owner partnerships, employer branding, reporting, process improvements and more.<br /><br />The Talent Team consists of our Head of Talent, Talent Manager and Talent Administrator. As a team, we believe in offering a superb candidate experience for everyone that takes part in our hiring process, whether that ends at the application stage or on their first day with us. We strive to offer an experience for candidates that is transparent and efficient as well as an opportunity for self-discovery along the way.<br /><br />This role is most complimentary to someone who excels in a fast-paced atmosphere and is results driven. They will also be excited by solving challenges, building processes and bringing new people into an company and community where they will thrive.<br /><br />This is a unique opportunity to grow our team and be a part of a disruptive category of music making devices we are creating called ‘Connected Music’ - a network of hardware and software, platform and developer products that will revolutionise how music is made. Join us to find more talented team members to help achieve our mission.<br /><br />What you’ll do:<br /><br />Develop, optimise and implement innovative methods to attract and source top talent, building and maintaining passive and active talent pools for a range of technical and non-technical roles across the business<br />Partner with key stakeholders and departments to understand their strategic direction and create appropriate short, medium and long term sourcing strategies to support this vision<br />Craft thoughtful, informative and tailored approaches to prospective candidates<br />Conduct phone screenings of prospective candidates sourced ahead of entering them into the hiring process<br />Ensure every conversation with a prospective candidate delivers a strong candidate and brand experience<br />Collaborate closely with the entire Talent Team on providing superb candidate and role owner experiences<br />Continuously develop a network of talent and industry contacts via direct sourcing as well as attend relevant meetups and industry events<br />Be an ambassador for the Talent Team, both internally and externally, promoting ROLI as a leading employer  <br />Utilise sourcing and recruitment data to inform sourcing strategies and decision making<br />Be responsible and accountable for the accuracy of any prospective and sourced candidate data in our CRM and Applicant Tracking System (Greenhouse)<br /><br />What you’ll need:<br /><br />Proven experience and success hiring across a range of roles in a startup or fast-paced technology driven organisation<br />A balanced approach when screening and assessing the chemistry of a candidate’s fit for a position and their motivation alongside selling an opportunity<br />Working knowledge and experience with Applicant Tracking Systems (we use Greenhouse), social media and candidate platforms and hiring process workflows<br />An adept understanding of the current UK tech talent market<br />Resilience and the ability to manage competing demands, multiple searches, changing priorities and challenging deadlines with speed<br />Fantastic organisation skills with a methodical approach alongside a flexible attitude<br />An interest in sharing and receiving knowledge and feedback to grow the collective understanding and skill set of the Talent Team<br />An inquisitive mind and demonstrable examples of implementing proactive solutions<br />Excellent interpersonal and communication (both written and verbal) skills and the ability to work effectively with employees at all levels<br />A passion for music, technology, the arts and/or startups<br /><br />Bonus points:<br /><br />Experience as an in-house Recruiter<br />Proficiency in Google Suite and Apple computers<br />Experience recruiting at a high-growth, VC backed startup<br /><br />ROLI offers:<br /><br />The opportunity to work with the leading, progressive minds within technology, hardware, and music creation to directly impact the way we create and interact with music<br />A range of meaningful benefits including:<br />Generous parental leave policy<br />Flexible and remote work options<br />Wellness programme including weekly massages, guided meditation and yoga<br />Monthly “Friends and Family dinners”<br />Quarterly “Family Days”<br />A competitive health care cash plan<br />Daily complimentary homemade vegetarian lunch, as well as freshly baked bread, a breakfast bar and limitless home­made GOLDnola<br />The opportunity to nurture a new skill set in a 30 minute skill sharing session<br />A dedicated company-wide Hack Day every four weeks<br />2 social impact days and 20 hours per year dedicated to volunteering within the local community<br />A ‘Lending Library’ and generous team discount across all ROLI products<br />State of the art laptop of your choice and relevant software licenses for your role and beyond<br />A company backed pension scheme<br />A generous bike-to-work scheme plus in-house bike storage  A competitive salary according to your level of experience<br /><br />To learn more about us and our culture, check out:<br /><br />Profile on ROLI Culture in The Guardian<br />See the Seaboard in action<br />Song maker kit with Marco Parisi<br />BLOCKS the modular music studio<br />Balderton Podcast - ROLI's company culture & building a unique team<br />Pharrell joins the team!<br />@ROLICareers<br />@CafeROLI"
  }
]
}
